pymzn/__init__.py
pymzn/__main__.py
pymzn/aio.py
pymzn/config.py
pymzn/log.py
pymzn/templates.py
pymzn/dzn/__init__.py
pymzn/dzn/marsh.py
pymzn/dzn/parse.py
pymzn/mzn/__init__.py
pymzn/mzn/minizinc.py
pymzn/mzn/output.py
pymzn/mzn/process.py
pymzn/mzn/rewrap.py
pymzn/mzn/solvers.py
pymzn/mzn/templates.py
pymzn/mzn/aio/__init__.py
pymzn/mzn/aio/minizinc.py
pymzn/mzn/aio/output.py
pymzn/mzn/aio/process.py
pymzn-0.18.3.dist-info/LICENSE
pymzn-0.18.3.dist-info/METADATA
pymzn-0.18.3.dist-info/WHEEL
pymzn-0.18.3.dist-info/entry_points.txt
pymzn-0.18.3.dist-info/top_level.txt
pymzn-0.18.3.dist-info/RECORD
