Metadata-Version: 2.1
Name: pymzn
Version: 0.18.3
Summary: A Python wrapper for the MiniZinc tool pipeline.
Home-page: https://github.com/paolodragone/pymzn
Author: Paolo Dragone
Author-email: dragone.paolo@gmail.com
License: MIT
Platform: any
Classifier: Programming Language :: Python
Classifier: Programming Language :: Python :: 3
Classifier: Programming Language :: Python :: 3.5
Classifier: Development Status :: 4 - Beta
Classifier: Natural Language :: English
Classifier: Environment :: Console
Classifier: Intended Audience :: Developers
Classifier: License :: OSI Approved :: MIT License
Classifier: Operating System :: OS Independent
Classifier: Topic :: Software Development :: Libraries :: Python Modules
